redvox/__init__.py
redvox/settings.py
redvox/api1000/__init__.py
redvox/api1000/errors.py
redvox/api1000/common/__init__.py
redvox/api1000/common/common.py
redvox/api1000/common/decorators.py
redvox/api1000/common/generic.py
redvox/api1000/common/lz4.py
redvox/api1000/common/mapping.py
redvox/api1000/common/metadata.py
redvox/api1000/common/typing.py
redvox/api1000/gui/__init__.py
redvox/api1000/gui/image_viewer.py
redvox/api1000/proto/__init__.py
redvox/api1000/proto/redvox_api_m_pb2.py
redvox/api1000/proto/redvox_api_m_pb2.pyi
redvox/api1000/wrapped_redvox_packet/__init__.py
redvox/api1000/wrapped_redvox_packet/event_streams.py
redvox/api1000/wrapped_redvox_packet/ml.py
redvox/api1000/wrapped_redvox_packet/station_information.py
redvox/api1000/wrapped_redvox_packet/timing_information.py
redvox/api1000/wrapped_redvox_packet/wrapped_packet.py
redvox/api1000/wrapped_redvox_packet/sensors/__init__.py
redvox/api1000/wrapped_redvox_packet/sensors/audio.py
redvox/api1000/wrapped_redvox_packet/sensors/image.py
redvox/api1000/wrapped_redvox_packet/sensors/location.py
redvox/api1000/wrapped_redvox_packet/sensors/sensors.py
redvox/api1000/wrapped_redvox_packet/sensors/single.py
redvox/api1000/wrapped_redvox_packet/sensors/xyz.py
redvox/api1000/wrapped_redvox_packet/sensors/derived/__init__.py
redvox/api1000/wrapped_redvox_packet/sensors/derived/movement.py
redvox/api900/__init__.py
redvox/api900/concat.py
redvox/api900/constants.py
redvox/api900/deprecation.py
redvox/api900/exceptions.py
redvox/api900/location_analyzer.py
redvox/api900/migrations.py
redvox/api900/reader.py
redvox/api900/reader_utils.py
redvox/api900/stat_utils.py
redvox/api900/summarize.py
redvox/api900/types.py
redvox/api900/wrapped_redvox_packet.py
redvox/api900/lib/__init__.py
redvox/api900/lib/api900_pb2.py
redvox/api900/lib/api900_pb2.pyi
redvox/api900/qa/__init__.py
redvox/api900/qa/gap_detection.py
redvox/api900/sensors/__init__.py
redvox/api900/sensors/accelerometer_sensor.py
redvox-3.8.8.dist-info/licenses/LICENSE
redvox-3.8.8.dist-info/METADATA
redvox-3.8.8.dist-info/WHEEL
redvox-3.8.8.dist-info/entry_points.txt
redvox-3.8.8.dist-info/top_level.txt
redvox-3.8.8.dist-info/RECORD
