Metadata-Version: 2.4
Name: redvox
Version: 3.8.8
Summary: Library for working with RedVox files. 
Author-email: "RedVox, Inc" <support@redvox.io>
License: 
Project-URL: homepage, https://github.com/RedVoxInc/redvox-python-sdk
Project-URL: PyPI, https://pypi.org/project/redvox/
Requires-Python: >=3.9
License-File: LICENSE
Requires-Dist: cython>=3.0.11
Requires-Dist: dataclasses-json>=0.6.7
Requires-Dist: fastkml>=1.1.0
Requires-Dist: lxml>=5.3.0
Requires-Dist: lz4>=4.3.3
Requires-Dist: numpy>=2.2.2
Requires-Dist: pandas>=2.2.3
Requires-Dist: protobuf>=4.25.6
Requires-Dist: psutil>=6.1.1
Requires-Dist: pyarrow>=18.1.0
Requires-Dist: pyserde>=0.23.0
Requires-Dist: requests>=2.32.3
Requires-Dist: scipy>=1.15.0
Requires-Dist: toml>=0.10.2
Requires-Dist: tomli>=2.2.1
Requires-Dist: tomli-w>=1.1.0
Requires-Dist: websocket-client>=1.8.0
Provides-Extra: gui
Requires-Dist: PySide6>=6.5.0; extra == "gui"
Requires-Dist: matplotlib>=3.10.0; extra == "gui"
Provides-Extra: native
Requires-Dist: redvox_native==0.2.3; extra == "native"
Provides-Extra: full
Requires-Dist: PySide6>=6.5.0; extra == "full"
Requires-Dist: matplotlib>=3.9.1; extra == "full"
Requires-Dist: redvox_native==0.2.3; extra == "full"
Dynamic: license-file
